aws_hello_creds.py
hello_crypto.py
security_config.py
security_utils.py
tests/__init__.py
tests/conftest.py
tests/test_aws_hello_creds.py
tests/test_hello_crypto.py
tests/test_security_utils.py
winhello_crypto-2.2.0.dist-info/licenses/LICENSE
winhello_crypto-2.2.0.dist-info/METADATA
winhello_crypto-2.2.0.dist-info/WHEEL
winhello_crypto-2.2.0.dist-info/entry_points.txt
winhello_crypto-2.2.0.dist-info/top_level.txt
winhello_crypto-2.2.0.dist-info/RECORD
