Metadata-Version: 2.4
Name: winhello-crypto
Version: 2.2.0
Summary: Enterprise-Grade AWS Credential Security with Windows Hello Biometric Authentication
Home-page: https://github.com/SergeDubovsky/WinHello-Crypto
Author: Serge Dubovsky
Author-email: Serge Dubovsky <serge@lavinna.com>
License: Apache-2.0
Project-URL: Homepage, https://github.com/SergeDubovsky/WinHello-Crypto
Project-URL: Repository, https://github.com/SergeDubovsky/WinHello-Crypto
Project-URL: Bug Reports, https://github.com/SergeDubovsky/WinHello-Crypto/issues
Project-URL: Documentation, https://github.com/SergeDubovsky/WinHello-Crypto/blob/main/README.md
Keywords: windows-hello,biometric,authentication,encryption,aws,credentials,security,cryptography
Platform: Windows
Classifier: Development Status :: 4 - Beta
Classifier: Intended Audience :: Developers
Classifier: Intended Audience :: System Administrators
Classifier: License :: OSI Approved :: Apache Software License
Classifier: Operating System :: Microsoft :: Windows :: Windows 10
Classifier: Operating System :: Microsoft :: Windows :: Windows 11
Classifier: Programming Language :: Python :: 3
Classifier: Programming Language :: Python :: 3.7
Classifier: Programming Language :: Python :: 3.8
Classifier: Programming Language :: Python :: 3.9
Classifier: Programming Language :: Python :: 3.10
Classifier: Programming Language :: Python :: 3.11
Classifier: Programming Language :: Python :: 3.12
Classifier: Topic :: Security :: Cryptography
Classifier: Topic :: System :: Systems Administration :: Authentication/Directory
Classifier: Topic :: Utilities
Requires-Python: >=3.7
License-File: LICENSE
Requires-Dist: cryptography<46.0.0,>=45.0.6
Requires-Dist: winrt-runtime<4.0.0,>=3.2.0; platform_system == "Windows"
Requires-Dist: winrt-Windows.Security.Credentials<4.0.0,>=3.2.0; platform_system == "Windows"
Requires-Dist: winrt-Windows.Storage.Streams<4.0.0,>=3.2.0; platform_system == "Windows"
Provides-Extra: dev
Requires-Dist: pytest<9.0.0,>=8.3.0; extra == "dev"
Requires-Dist: pytest-asyncio<1.0.0,>=0.24.0; extra == "dev"
Requires-Dist: pytest-cov<6.0.0,>=5.0.0; extra == "dev"
Requires-Dist: black<25.0.0,>=24.0.0; extra == "dev"
Requires-Dist: flake8<8.0.0,>=7.1.0; extra == "dev"
Requires-Dist: mypy<2.0.0,>=1.11.0; extra == "dev"
Provides-Extra: security
Requires-Dist: bandit<2.0.0,>=1.7.5; extra == "security"
Requires-Dist: safety<3.3.0,>=3.2.0; extra == "security"
Provides-Extra: docs
Requires-Dist: sphinx<8.0.0,>=7.0.0; extra == "docs"
Requires-Dist: sphinx-rtd-theme<3.0.0,>=2.0.0; extra == "docs"
Dynamic: author
Dynamic: home-page
Dynamic: license-file
Dynamic: platform
Dynamic: requires-python
